{
  "hero": {
    "title": "Tharuwana Meelad Fest",
    "subtitle": "Jalsa Meelad — August 2 & 3, 2026 (Saturday & Sunday) · Tharuwana",
    "ayah": "طَلَبُ الْعِلْمِ فَرِيضَةْ عَلَى كُلِّ مُسْلِمِ",
    "tag1": "Boys & Girls Competitions",
    "tag2": "4 Categories",
    "tag3": "Live Results",
    "posterTemplate": "classic"
  },
  "categories": [
    "Sub Junior",
    "Junior",
    "Senior",
    "Super Senior"
  ],
  "limits": {
    "maxIndividual": 4,
    "maxGroup": 2
  },
  "teams": [
    {
      "id": "t1",
      "name": "Zumurrud Green",
      "leader": "Aliyar K.",
      "assistant": "Fahad P.",
      "color": "#1F7A57"
    },
    {
      "id": "t2",
      "name": "Dahab Gold",
      "leader": "Nihal M.",
      "assistant": "Rizwan T.",
      "color": "#C9A227"
    },
    {
      "id": "t3",
      "name": "Yaqoot Crimson",
      "leader": "Sameer V.",
      "assistant": "Ashraf N.",
      "color": "#8B2635"
    },
    {
      "id": "t4",
      "name": "Lazward Blue",
      "leader": "Basith K.",
      "assistant": "Hamza C.",
      "color": "#2C4B8B"
    }
  ],
  "events": [
    {
      "id": "e1",
      "name": "Quran Recitation",
      "category": "Sub Junior",
      "type": "Individual",
      "gender": "General",
      "status": "pending",
      "resultStatus": "Published",
      "judges": []
    },
    {
      "id": "e2",
      "name": "Mono Act",
      "category": "Junior",
      "type": "Individual",
      "gender": "Boys",
      "status": "pending",
      "resultStatus": "Pending",
      "judges": []
    },
    {
      "id": "e3",
      "name": "Group Nasheed",
      "category": "Senior",
      "type": "Group",
      "gender": "General",
      "status": "pending",
      "resultStatus": "Pending",
      "judges": []
    },
    {
      "id": "e4",
      "name": "Speech (Malayalam)",
      "category": "Junior",
      "type": "Individual",
      "gender": "Girls",
      "status": "pending",
      "resultStatus": "Pending",
      "judges": []
    },
    {
      "id": "e5",
      "name": "Arabic Elocution",
      "category": "Senior",
      "type": "Individual",
      "gender": "General",
      "status": "pending",
      "resultStatus": "Pending",
      "judges": []
    },
    {
      "id": "e6",
      "name": "Drawing",
      "category": "Sub Junior",
      "type": "Individual",
      "gender": "General",
      "status": "pending",
      "resultStatus": "Pending",
      "judges": []
    },
    {
      "id": "e7",
      "name": "Skit",
      "category": "Super Senior",
      "type": "Group",
      "gender": "General",
      "status": "pending",
      "resultStatus": "Pending",
      "judges": []
    },
    {
      "id": "e8",
      "name": "Islamic Quiz",
      "category": "Junior",
      "type": "Group",
      "gender": "General",
      "status": "pending",
      "resultStatus": "Pending",
      "judges": []
    },
    {
      "id": "e9",
      "name": "Nasheed Solo",
      "category": "Senior",
      "type": "Individual",
      "gender": "Boys",
      "status": "pending",
      "resultStatus": "Pending",
      "judges": []
    },
    {
      "id": "e10",
      "name": "Rangoli",
      "category": "Junior",
      "type": "Individual",
      "gender": "Girls",
      "status": "pending",
      "resultStatus": "Pending",
      "judges": []
    }
  ],
  "students": [
    {
      "id": "s1",
      "name": "Muhammad Ayaan",
      "cls": "5",
      "phone": "9895000001",
      "gender": "Boys",
      "team": "t1",
      "category": "Sub Junior",
      "chestNo": "SJB-01",
      "events": [
        "e1",
        "e6"
      ]
    },
    {
      "id": "s2",
      "name": "Fathima Rizana",
      "cls": "6",
      "phone": "9895000002",
      "gender": "Girls",
      "team": "t2",
      "category": "Junior",
      "chestNo": "JRG-01",
      "events": [
        "e4",
        "e10"
      ]
    },
    {
      "id": "s3",
      "name": "Abdul Basith",
      "cls": "9",
      "phone": "9895000003",
      "gender": "Boys",
      "team": "t3",
      "category": "Senior",
      "chestNo": "SRB-01",
      "events": [
        "e5",
        "e9",
        "e3"
      ]
    },
    {
      "id": "s4",
      "name": "Ameen Siddique",
      "cls": "6",
      "phone": "9895000004",
      "gender": "Boys",
      "team": "t4",
      "category": "Junior",
      "chestNo": "JRB-01",
      "events": [
        "e2",
        "e8"
      ]
    },
    {
      "id": "s5",
      "name": "Hafsa Nazrin",
      "cls": "9",
      "phone": "9895000005",
      "gender": "Girls",
      "team": "t1",
      "category": "Senior",
      "chestNo": "SRG-01",
      "events": [
        "e3",
        "e5"
      ]
    }
  ],
  "results": {
    "e1": {
      "first": {
        "studentId": "s1"
      },
      "second": null,
      "third": null
    }
  },
  "gallery": [
    {
      "id": "g1",
      "caption": "Opening Ceremony",
      "color": "#1F7A57",
      "url": null
    },
    {
      "id": "g2",
      "caption": "Quran Recitation Stage",
      "color": "#C9A227",
      "url": null
    },
    {
      "id": "g3",
      "caption": "Group Nasheed",
      "color": "#8B2635",
      "url": null
    },
    {
      "id": "g4",
      "caption": "Arabic Elocution",
      "color": "#2C4B8B",
      "url": null
    },
    {
      "id": "g5",
      "caption": "Green Room",
      "color": "#155E43",
      "url": null
    },
    {
      "id": "g6",
      "caption": "Prize Prep",
      "color": "#9C7A1E",
      "url": null
    },
    {
      "id": "g7",
      "caption": "Volunteers",
      "color": "#6B2E3A",
      "url": null
    },
    {
      "id": "g8",
      "caption": "Evening Lights",
      "color": "#1F4B7A",
      "url": null
    },
    {
      "id": "g9",
      "caption": "Registration Desk",
      "color": "#3A5B4B",
      "url": null
    }
  ],
  "judges": [
    "Ustadh Rasheed",
    "Ustadh Nawfal"
  ],
  "marks": {}
}
